{
  "placeholderImages": [
    {
      "id": "1",
      "description": "Avatar for Alice",
      "imageUrl": "https://picsum.photos/seed/1/100/100",
      "imageHint": "woman portrait"
    },
    {
      "id": "2",
      "description": "Avatar for Bob",
      "imageUrl": "https://picsum.photos/seed/2/100/100",
      "imageHint": "man portrait"
    },
    {
      "id": "3",
      "description": "Avatar for Charlie",
      "imageUrl": "https://picsum.photos/seed/3/100/100",
      "imageHint": "person portrait"
    },
    {
      "id": "4",
      "description": "Avatar for Diana",
      "imageUrl": "https://picsum.photos/seed/4/100/100",
      "imageHint": "woman smiling"
    },
    {
      "id": "5",
      "description": "Avatar for Eve",
      "imageUrl": "https://picsum.photos/seed/5/100/100",
      "imageHint": "person thinking"
    },
    {
      "id": "99",
      "description": "Avatar for Admin",
      "imageUrl": "https://picsum.photos/seed/99/100/100",
      "imageHint": "abstract geometric"
    },
    {
      "id": "101",
      "description": "Avatar for Project Phoenix Group",
      "imageUrl": "https://picsum.photos/seed/101/100/100",
      "imageHint": "phoenix bird"
    },
    {
      "id": "102",
      "description": "Avatar for Marketing Team Group",
      "imageUrl": "https://picsum.photos/seed/102/100/100",
      "imageHint": "graph arrows"
    },
    {
      "id": "103",
      "description": "Avatar for General Group",
      "imageUrl": "https://picsum.photos/seed/103/100/100",
      "imageHint": "people talking"
    },
    {
      "id": "hero-image",
      "description": "Hero section preview image",
      "imageUrl": "https://picsum.photos/seed/110/1280/720",
      "imageHint": "dashboard application"
    }
  ]
}
